{
"companyName": "DefaultCompany",
"productName": "BioMol2022",
"productVersion": "0.1",
"dataUrl": "BMADNAnebula2.data.unityweb",
"wasmCodeUrl": "BMADNAnebula2.wasm.code.unityweb",
"wasmFrameworkUrl": "BMADNAnebula2.wasm.framework.unityweb",
"graphicsAPI": ["WebGL 2.0","WebGL 1.0"],
"webglContextAttributes": {"preserveDrawingBuffer": false},
"splashScreenStyle": "Dark",
"backgroundColor": "#231F20",
"cacheControl": {"default": "must-revalidate"},
"developmentBuild": false,
"multithreading": false,
"unityVersion": "2019.4.4f1"
}